{
    "uid": "9f8fa37e-ba94-4685-aab9-fe02c766c1cf",
    "name": "2_DecisionTree",
    "preprocessing": [
        {
            "remove_columns": [
                "feature_6",
                "feature_9",
                "feature_18",
                "feature_20",
                "feature_21",
                "feature_26",
                "feature_35",
                "feature_37",
                "feature_45",
                "feature_47",
                "feature_48",
                "feature_49",
                "feature_51",
                "feature_54",
                "feature_55",
                "feature_57",
                "feature_62",
                "feature_64",
                "feature_65",
                "feature_72",
                "feature_73",
                "feature_85",
                "feature_86",
                "feature_89",
                "feature_90",
                "feature_93",
                "feature_94",
                "feature_105",
                "feature_107",
                "feature_113",
                "feature_116",
                "feature_120",
                "feature_121",
                "feature_122",
                "feature_123",
                "feature_124",
                "feature_127",
                "feature_129",
                "feature_140",
                "feature_141",
                "feature_145",
                "feature_146",
                "feature_151",
                "feature_153",
                "feature_157"
            ],
            "categorical_y": {
                "0": 0,
                "1": 1,
                "2": 2,
                "3": 3
            },
            "ml_task": "multiclass_classification",
            "params": {
                "columns_preprocessing": {
                    "feature_6": [
                        "remove_column"
                    ],
                    "feature_9": [
                        "remove_column"
                    ],
                    "feature_18": [
                        "remove_column"
                    ],
                    "feature_20": [
                        "remove_column"
                    ],
                    "feature_21": [
                        "remove_column"
                    ],
                    "feature_26": [
                        "remove_column"
                    ],
                    "feature_35": [
                        "remove_column"
                    ],
                    "feature_37": [
                        "remove_column"
                    ],
                    "feature_45": [
                        "remove_column"
                    ],
                    "feature_47": [
                        "remove_column"
                    ],
                    "feature_48": [
                        "remove_column"
                    ],
                    "feature_49": [
                        "remove_column"
                    ],
                    "feature_51": [
                        "remove_column"
                    ],
                    "feature_54": [
                        "remove_column"
                    ],
                    "feature_55": [
                        "remove_column"
                    ],
                    "feature_57": [
                        "remove_column"
                    ],
                    "feature_62": [
                        "remove_column"
                    ],
                    "feature_64": [
                        "remove_column"
                    ],
                    "feature_65": [
                        "remove_column"
                    ],
                    "feature_72": [
                        "remove_column"
                    ],
                    "feature_73": [
                        "remove_column"
                    ],
                    "feature_85": [
                        "remove_column"
                    ],
                    "feature_86": [
                        "remove_column"
                    ],
                    "feature_89": [
                        "remove_column"
                    ],
                    "feature_90": [
                        "remove_column"
                    ],
                    "feature_93": [
                        "remove_column"
                    ],
                    "feature_94": [
                        "remove_column"
                    ],
                    "feature_105": [
                        "remove_column"
                    ],
                    "feature_107": [
                        "remove_column"
                    ],
                    "feature_113": [
                        "remove_column"
                    ],
                    "feature_116": [
                        "remove_column"
                    ],
                    "feature_120": [
                        "remove_column"
                    ],
                    "feature_121": [
                        "remove_column"
                    ],
                    "feature_122": [
                        "remove_column"
                    ],
                    "feature_123": [
                        "remove_column"
                    ],
                    "feature_124": [
                        "remove_column"
                    ],
                    "feature_127": [
                        "remove_column"
                    ],
                    "feature_129": [
                        "remove_column"
                    ],
                    "feature_140": [
                        "remove_column"
                    ],
                    "feature_141": [
                        "remove_column"
                    ],
                    "feature_145": [
                        "remove_column"
                    ],
                    "feature_146": [
                        "remove_column"
                    ],
                    "feature_151": [
                        "remove_column"
                    ],
                    "feature_153": [
                        "remove_column"
                    ],
                    "feature_157": [
                        "remove_column"
                    ]
                },
                "target_preprocessing": [
                    "na_exclude",
                    "categorical_to_int"
                ],
                "ml_task": "multiclass_classification"
            }
        }
    ],
    "learners": [
        {
            "library_version": "1.5.0",
            "algorithm_name": "Decision Tree",
            "algorithm_short_name": "Decision Tree",
            "uid": "198d1302-f6f1-4235-b272-f9d87932e9a9",
            "params": {
                "model_type": "Decision Tree",
                "ml_task": "multiclass_classification",
                "n_jobs": -1,
                "seed": 1235,
                "criterion": "gini",
                "max_depth": 3,
                "num_class": 4,
                "explain_level": 2
            },
            "name": "learner_fold_0"
        }
    ],
    "params": {
        "additional": {
            "trees_in_step": 1,
            "train_cant_improve_limit": 0,
            "max_steps": 1,
            "max_rows_limit": null,
            "max_cols_limit": null
        },
        "preprocessing": {
            "columns_preprocessing": {
                "feature_6": [
                    "remove_column"
                ],
                "feature_9": [
                    "remove_column"
                ],
                "feature_18": [
                    "remove_column"
                ],
                "feature_20": [
                    "remove_column"
                ],
                "feature_21": [
                    "remove_column"
                ],
                "feature_26": [
                    "remove_column"
                ],
                "feature_35": [
                    "remove_column"
                ],
                "feature_37": [
                    "remove_column"
                ],
                "feature_45": [
                    "remove_column"
                ],
                "feature_47": [
                    "remove_column"
                ],
                "feature_48": [
                    "remove_column"
                ],
                "feature_49": [
                    "remove_column"
                ],
                "feature_51": [
                    "remove_column"
                ],
                "feature_54": [
                    "remove_column"
                ],
                "feature_55": [
                    "remove_column"
                ],
                "feature_57": [
                    "remove_column"
                ],
                "feature_62": [
                    "remove_column"
                ],
                "feature_64": [
                    "remove_column"
                ],
                "feature_65": [
                    "remove_column"
                ],
                "feature_72": [
                    "remove_column"
                ],
                "feature_73": [
                    "remove_column"
                ],
                "feature_85": [
                    "remove_column"
                ],
                "feature_86": [
                    "remove_column"
                ],
                "feature_89": [
                    "remove_column"
                ],
                "feature_90": [
                    "remove_column"
                ],
                "feature_93": [
                    "remove_column"
                ],
                "feature_94": [
                    "remove_column"
                ],
                "feature_105": [
                    "remove_column"
                ],
                "feature_107": [
                    "remove_column"
                ],
                "feature_113": [
                    "remove_column"
                ],
                "feature_116": [
                    "remove_column"
                ],
                "feature_120": [
                    "remove_column"
                ],
                "feature_121": [
                    "remove_column"
                ],
                "feature_122": [
                    "remove_column"
                ],
                "feature_123": [
                    "remove_column"
                ],
                "feature_124": [
                    "remove_column"
                ],
                "feature_127": [
                    "remove_column"
                ],
                "feature_129": [
                    "remove_column"
                ],
                "feature_140": [
                    "remove_column"
                ],
                "feature_141": [
                    "remove_column"
                ],
                "feature_145": [
                    "remove_column"
                ],
                "feature_146": [
                    "remove_column"
                ],
                "feature_151": [
                    "remove_column"
                ],
                "feature_153": [
                    "remove_column"
                ],
                "feature_157": [
                    "remove_column"
                ]
            },
            "target_preprocessing": [
                "na_exclude",
                "categorical_to_int"
            ],
            "ml_task": "multiclass_classification"
        },
        "validation_strategy": {
            "validation_type": "split",
            "train_ratio": 0.75,
            "shuffle": true,
            "stratify": true,
            "X_path": "AutoML_Results_smote\\X.data",
            "y_path": "AutoML_Results_smote\\y.data",
            "results_path": "AutoML_Results_smote"
        },
        "learner": {
            "model_type": "Decision Tree",
            "ml_task": "multiclass_classification",
            "n_jobs": -1,
            "seed": 1235,
            "criterion": "gini",
            "max_depth": 3,
            "num_class": 4,
            "explain_level": 2
        },
        "automl_random_state": 1234,
        "ml_task": "multiclass_classification",
        "explain_level": 2,
        "name": "2_DecisionTree",
        "status": "initialized",
        "final_loss": null,
        "train_time": null,
        "data_type": "original",
        "max_time_for_learner": 360.0
    },
    "saved": [
        "2_DecisionTree\\learner_fold_0.decision_tree"
    ],
    "predictions_fname": "2_DecisionTree\\predictions_validation.csv",
    "metric_name": "logloss",
    "final_loss": "1.446354195173939",
    "train_time": 28.054880380630493,
    "is_stacked": false,
    "joblib_version": "1.4.2"
}